tests/__init__.py
tests/conftest.py
tests/test_notification.py
tests/test_utils.py
tests/test_validation.py
tests/test_verification.py
tests/tfr_utils.py
tfr/__init__.py
tfr/data/VERSION
tfr/data/options.json
tfr/provider/__init__.py
tfr/provider/models.py
tfr/provider/tfr.py
tfr/provider/utils.py
tesla_ce_provider_fr_tfr-0.0.8.dist-info/LICENSE
tesla_ce_provider_fr_tfr-0.0.8.dist-info/METADATA
tesla_ce_provider_fr_tfr-0.0.8.dist-info/WHEEL
tesla_ce_provider_fr_tfr-0.0.8.dist-info/top_level.txt
tesla_ce_provider_fr_tfr-0.0.8.dist-info/RECORD
