Metadata-Version: 2.1
Name: tesla-ce-provider-fr-tfr
Version: 0.0.8
Summary: TeSLA CE Face Recognition Provider
Home-page: https://tesla-ce.github.io
Author: Xavier Baro
Author-email: xbaro@uoc.edu
License: UNKNOWN
Project-URL: Documentation, https://tesla-ce.github.io/provider-fr-tfr/
Project-URL: Source, https://github.com/tesla-ce/provider-fr-tfr
Platform: UNKNOWN
Classifier: Programming Language :: Python :: 3
Classifier: License :: OSI Approved :: GNU Affero General Public License v3 or later (AGPLv3+)
Classifier: Operating System :: POSIX :: Linux
Requires-Python: >=3.6
License-File: LICENSE
Requires-Dist: face-recognition
Requires-Dist: tesla-ce-provider (>=0.0.9)
